{
  "last_run": "2026-04-19T03:52:59Z",
  "last_run_id": "24620382255",
  "monthly_summary_issue": "open #62 (April 2026)",
  "comments_made": [],
  "prs_created": [
    {
      "branch": "repo-assist/bindings-queue-2026-04",
      "title": "feat: add queue module bindings and tests",
      "status": "patch-only",
      "description": "Added Fable.Beam.Queue with 14 ImportAll bindings (new, is_empty, is_queue, len, in, in_r, head, last, tail, init, to_list, from_list, member, reverse, join, filter) and 5 Emit wrappers (out, outRear, peek, peekRear, split), plus 26 tests. Also backfilled README. Patch in run 24620382255.",
      "pr_number": null
    },
    {
      "branch": "repo-assist/bindings-string-2026-04",
      "title": "feat: add string module bindings and tests",
      "status": "patch-only",
      "description": "Added Fable.Beam.String with 28 bindings and 22 tests. Patch in run 24595953899.",
      "pr_number": null
    },
    {
      "branch": "repo-assist/eng-ci-caching-2026-04",
      "title": "chore: add NuGet and rebar3 dependency caching to CI",
      "status": "patch-only",
      "description": "Push rejected (workflows permission). Patch in issue #67 for manual application."
    }
  ],
  "backlog_cursor": null,
  "notes": "Open issues: #67 (CI caching info), #62 (monthly summary). No user-filed issues. String bindings patch applied manually by maintainer (PR #71 merged, release PR #72 open). Queue bindings patch in run 24620382255. CI caching patch still needs manual application (#67). README updated with all recent modules.",
  "future_bindings_ideas": ["uri_string", "base64", "calendar", "re", "rand"]
}
